turboshtein.cpython-310-darwin.so
turboshtein-0.0.4.dist-info/LICENSE
turboshtein-0.0.4.dist-info/METADATA
turboshtein-0.0.4.dist-info/WHEEL
turboshtein-0.0.4.dist-info/top_level.txt
turboshtein-0.0.4.dist-info/RECORD
