Metadata-Version: 2.1
Name: turboshtein
Version: 0.0.4
Summary: Levenshtein edit distance computed quickly
Home-page: https://githubcom/nathanrooy/turboshtein
Author: Nathan A. Rooy
Author-email: nathanrooy@gmail.com
License: MIT License
Keywords: levenshtein distance
Classifier: License :: OSI Approved :: MIT License
Classifier: Operating System :: OS Independent
Classifier: Programming Language :: Python :: 3
Classifier: Programming Language :: C
Requires-Python: >=3.4
License-File: LICENSE
